{
    "configuration": {
        "bounds_handling": "periodic",
        "cognitive_coefficient": 2.905405139888455,
        "common_ratio": 0.6,
        "convergence_time": 150,
        "convergence_tolarance": 0.005,
        "flow_smoothing": 0,
        "fraction_rbo_init": 0.5,
        "inertia_weight": 0.4424113459034113,
        "limit_zones_penalty": 0.0,
        "max_iterations": null,
        "max_relvar": 1.0,
        "max_time": 900,
        "maximize_final_vol": false,
        "mode": "linear",
        "num_particles": 200,
        "prob_below_half": 0.15,
        "random_biased_flows": false,
        "random_biased_sorting": true,
        "social_coefficient": 0.4232260541405988,
        "startups_penalty": 0.0,
        "topology": "star",
        "topology_minkowski_p_norm": null,
        "topology_num_neighbors": null,
        "use_relvars": true,
        "volume_exceedance_bonus": 0.0,
        "volume_objectives": {},
        "volume_shortage_penalty": 0.0
    },
    "dams": [
        {
            "flows": [
                11.325502187460321,
                0.0,
                0.0,
                0.0,
                0.0,
                0.0,
                0.0,
                0.0,
                0.0,
                0.0,
                0.0,
                0.0,
                0.0,
                0.0,
                0.0,
                0.0,
                0.0,
                0.0,
                0.0,
                0.0,
                1.1355079318412755,
                0.0,
                0.5550708960634883,
                0.561596495777776,
                1.6934233599682598,
                0.0,
                0.0,
                0.5625724584126955,
                1.6996235355555513,
                0.0,
                0.0,
                11.06614824507936,
                0.0,
                8.084397349092695e-15,
                0.0,
                0.0,
                0.0,
                0.0,
                0.0,
                0.0,
                0.0,
                0.0,
                0.0,
                0.0,
                0.0,
                0.0,
                0.0,
                0.0,
                0.0,
                0.0,
                0.0,
                0.5478576517142938,
                1.6292254300317532,
                0.0,
                0.0,
                0.5477290987301644,
                1.093231861587297,
                0.0,
                3.482380575714277,
                0.0,
                0.0,
                0.0,
                0.0,
                6.291935493047624,
                0.0,
                0.0,
                0.0,
                0.0,
                0.0,
                0.0,
                0.0,
                3.1949778397460373,
                0.0,
                0.0,
                0.0,
                0.7854410636825357,
                1.5800384964761907,
                0.0,
                0.7968968058730146,
                0.8305146483174596,
                14.15,
                14.15,
                14.15,
                0.0,
                2.411356055555508,
                0.8053915520317484,
                0.7924581689841256,
                0.0,
                0.0,
                0.0,
                3.185531915238098,
                0.7998877668888923,
                0.7983898908571427,
                0.7930557557142796,
                0.7941784007301612,
                0.8047738965079366,
                0.0,
                1.6014945261587288,
                0.7994708484444466
            ],
            "id": "dam1",
            "objective_function_details": {
                "income_from_energy_eur": 321.1906327758282,
                "limit_zones": 1.0,
                "startups": 13.0,
                "total_income_eur": 321.1906327758282
            },
            "power": [
                0.7953574951772485,
                3.931434898756242,
                0.0,
                0.0,
                0.0,
                0.0,
                0.0,
                0.0,
                0.0,
                0.0,
                0.0,
                0.0,
                0.0,
                0.0,
                0.0,
                0.0,
                0.0,
                0.0,
                0.0,
                0.0,
                0.0,
                0.0,
                0.0,
                0.0,
                0.0,
                0.07580528344410356,
                0.0,
                0.0,
                0.0,
                0.07758950663469107,
                0.0,
                0.0,
                3.857159826055591,
                0.0,
                0.0,
                0.0,
                0.0,
                0.0,
                0.0,
                0.0,
                0.0,
                0.0,
                0.0,
                0.0,
                0.0,
                0.0,
                0.0,
                0.0,
                0.0,
                0.0,
                0.0,
                0.0,
                0.0,
                0.05733105900194341,
                0.0,
                0.0,
                0.0,
                0.0,
                0.0,
                0.826254166779095,
                0.0,
                0.0,
                0.0,
                0.0,
                2.182997876371258,
                0.0,
                0.0,
                0.0,
                0.0,
                0.0,
                0.0,
                0.0,
                0.6413051839106445,
                0.0,
                0.0,
                0.0,
                0.0,
                0.0431765457485441,
                0.0,
                0.0,
                0.0,
                4.6,
                4.6,
                4.6,
                0.0,
                0.2824046203037433,
                0.0,
                0.0,
                0.0,
                0.0,
                0.0,
                0.6352265565652575,
                0.0,
                0.0,
                0.0,
                0.0,
                0.0,
                0.0,
                0.04935094277949032
            ],
            "volume": [
                61181.31472719999,
                61680.397438914275,
                62194.38481325713,
                62701.583877571415,
                63212.06174234284,
                63724.62452125713,
                64234.78658519999,
                64748.232933199986,
                65264.36975665713,
                65773.67840482856,
                66286.17086228571,
                66796.40610882857,
                67301.76307797142,
                67812.52643022857,
                68328.70084199999,
                68846.68299451428,
                69355.7279568,
                69863.44009959999,
                70373.99063091427,
                70881.99999999999,
                70372.32057691427,
                70881.99999999999,
                70881.99999999999,
                70881.99999999999,
                69861.45579811427,
                70376.20736694285,
                70882.0,
                70882.0,
                69865.33380222858,
                70378.54157671428,
                70882.0,
                61416.588149657146,
                61919.41165054286,
                62424.58252545714,
                62932.940256371425,
                63432.17148419999,
                63931.75924317142,
                64430.13376997142,
                64927.29726665714,
                65422.27486188571,
                65919.83587394285,
                66417.73279897142,
                66908.98509697143,
                67401.45668462857,
                67896.0094042,
                68392.64325402858,
                68890.6650304,
                69391.00304485715,
                69888.95984022858,
                70387.81833637143,
                70882.0,
                70882.0,
                69906.32579145713,
                70396.01515179999,
                70881.99999999999,
                70881.99999999999,
                70381.07690111427,
                70881.99999999999,
                68254.33141654285,
                68763.7940064857,
                69383.66366774283,
                70133.83951851426,
                70881.99999999997,
                65921.46100302854,
                66613.63679331426,
                67318.73447879998,
                68032.0463961714,
                68746.31507894283,
                69461.50681105712,
                70166.2850565714,
                70881.99999999997,
                68731.7512272571,
                69456.5591504571,
                70171.2207162571,
                70881.99999999996,
                70881.99999999996,
                70166.70473457138,
                70881.99999999996,
                70881.99999999996,
                70844.68516128567,
                58816.76565494281,
                46788.984109457095,
                34755.14834477138,
                35479.62670194281,
                34045.0,
                34045.0,
                34045.0,
                34755.948016,
                35469.37447311429,
                36190.731646685716,
                34045.0,
                34045.0,
                34045.0,
                34045.00000000001,
                34045.00000000001,
                34045.00000000001,
                34766.55701262858,
                34045.000000000015,
                34045.000000000015
            ]
        },
        {
            "flows": [
                0.0,
                0.0,
                0.0,
                0.0,
                0.0,
                0.0,
                0.0,
                0.0,
                0.0,
                0.0,
                0.0,
                0.0,
                0.0,
                0.0,
                0.0,
                0.0,
                0.0,
                0.0,
                0.0,
                0.0,
                0.0,
                0.0,
                0.0,
                0.0,
                0.0,
                4.5272625154919093e-13,
                0.0,
                0.0,
                8.084397349092695e-15,
                8.084397349092695e-15,
                9.62016150879208e-06,
                1.8044374883174896e-11,
                1.134402636024687e-10,
                0.0,
                2.8699610589279068e-12,
                0.0,
                0.0,
                0.0,
                0.0,
                0.0,
                0.0,
                0.0,
                0.0,
                0.0,
                0.0,
                0.0,
                0.0,
                0.0,
                7.275957614183426e-14,
                2.8170996099813946e-08,
                4.481852455582056e-09,
                6.995795314045002e-06,
                4.397258977405727e-05,
                0.6256593360400116,
                0.06863756128718604,
                0.00027639297103936164,
                0.009079630521106689,
                7.130276773952776e-10,
                0.00017607126792427153,
                0.0026271641613210602,
                0.17720301756866522,
                0.010919855574021413,
                0.2801589870538656,
                0.36786531027027297,
                1.1129922576300385e-06,
                0.000701752878626899,
                4.2012300586470194e-05,
                1.7707090592011808e-07,
                0.0282684415250939,
                0.07676452920369532,
                0.0017372884980351147,
                1.1511181230334155,
                3.014484875777804,
                6.944723020722595,
                8.274228759606437,
                7.174187058222143,
                2.2669699917888484,
                6.0669277756566915,
                5.409653071107277,
                4.636994924994485,
                3.9720251978923504,
                3.40527673246535,
                4.948716375535587,
                6.101280093472362,
                7.053135950279433,
                0.6790118260822945,
                6.333913162169629,
                6.101116588271975,
                5.308001355997072,
                4.743008876360728,
                4.038293182247859,
                3.185534043686805,
                8.084397349092695e-15,
                1.598277657746035,
                0.0,
                1.5872341564444408,
                0.0,
                0.8047738965079366,
                1.6014945261587288
            ],
            "id": "dam2",
            "objective_function_details": {
                "income_from_energy_eur": 858.179202915532,
                "limit_zones": 7.0,
                "startups": 5.0,
                "total_income_eur": 858.179202915532
            },
            "power": [
                0.44893518454186365,
                0.4365118734691928,
                0.42616260013709983,
                0.0,
                0.0,
                0.0,
                0.0,
                0.0,
                0.0,
                0.0,
                0.0,
                0.0,
                0.0,
                0.0,
                0.0,
                0.0,
                0.0,
                0.0,
                0.0,
                0.0,
                0.0,
                0.0,
                0.0,
                0.0,
                0.0,
                0.0,
                0.0,
                0.0,
                0.0,
                0.0,
                0.0,
                0.0,
                0.0,
                0.0,
                0.0,
                0.0,
                0.0,
                0.0,
                0.0,
                0.0,
                0.0,
                0.0,
                0.0,
                0.0,
                0.0,
                0.0,
                0.0,
                0.0,
                0.0,
                0.0,
                0.0,
                0.0,
                0.0,
                0.0,
                0.0,
                0.0,
                0.0,
                0.0,
                0.0,
                0.0,
                0.0,
                0.0,
                0.0,
                0.0,
                0.0,
                0.0,
                0.0,
                0.0,
                0.0,
                0.0,
                0.0,
                0.0,
                0.0,
                0.0,
                0.0,
                0.0,
                2.1268467536472495,
                4.421175185160013,
                5.6,
                4.253244329723081,
                3.537727802815824,
                3.48,
                3.7340031553712407,
                3.48,
                2.6261830248612084,
                2.798372016588674,
                3.48,
                4.378935891267469,
                3.48,
                3.48,
                3.2336610613179637,
                4.262205802087155,
                3.7464998256475717,
                3.48,
                2.5999666088869797,
                0.0,
                0.0,
                0.0,
                0.0
            ],
            "volume": [
                20207.931633542856,
                30400.883602257145,
                30400.883602257145,
                30400.883602257145,
                30400.883602257145,
                30400.883602257145,
                30400.883602257145,
                30400.883602257145,
                30400.883602257145,
                30400.883602257145,
                30400.883602257145,
                30400.883602257145,
                30400.883602257145,
                30400.883602257145,
                30400.883602257145,
                30400.883602257145,
                30400.883602257145,
                30400.883602257145,
                30400.883602257145,
                30400.883602257145,
                30400.883602257145,
                31422.840740914293,
                31422.840740914293,
                31922.404547371432,
                32427.84139357143,
                33951.92241754246,
                33951.92241754246,
                33951.92241754246,
                34458.23763011388,
                35987.89881211387,
                35987.89015396851,
                35987.89015395227,
                45947.4235744216,
                45947.4235744216,
                45947.42357441902,
                45947.42357441902,
                45947.42357441902,
                45947.42357441902,
                45947.42357441902,
                45947.42357441902,
                45947.42357441902,
                45947.42357441902,
                45947.42357441902,
                45947.42357441902,
                45947.42357441902,
                45947.42357441902,
                45947.42357441902,
                45947.42357441902,
                45947.42357441896,
                45947.42354906506,
                45947.42354503139,
                45947.41724881561,
                46440.44956002768,
                47343.659044620246,
                47281.88523946178,
                47281.63648578784,
                47766.421007175995,
                48750.32968196284,
                48750.171217821706,
                51881.949288219366,
                51722.46657240757,
                51712.63870239095,
                51460.49561404247,
                51129.41683479922,
                56792.15777684905,
                56791.52619925829,
                56791.48838818776,
                56791.488228823946,
                56766.04663145136,
                56696.958555168036,
                56695.394995519804,
                55659.38868478973,
                55821.83235236114,
                49571.581633710804,
                42124.77575006501,
                35668.00739766508,
                34334.6313623694,
                30296.43101110695,
                25427.7432471104,
                21971.654939901076,
                19144.295445283675,
                28814.54638606486,
                37095.70164808283,
                44339.549563957706,
                37991.727208706216,
                39550.83701523211,
                34575.167566108015,
                29797.37498874895,
                25020.173768351586,
                20751.46577962693,
                17117.001915603858,
                17117.000000000022,
                17836.898990200018,
                17117.000000000015,
                17830.750180142866,
                17117.000000000015,
                17841.296506857158,
                17117.000000000015,
                17117.000000000015
            ]
        }
    ],
    "instance_datetimes": {
        "end_decisions": "2020-09-08 23:45",
        "start": "2020-09-08 00:00"
    },
    "instance_name": "Percentile00",
    "objective_function": 1179.36983569136,
    "objective_history": {
        "objective_values_eur": [
            1179.36983569136,
            1179.36983569136,
            1179.36983569136,
            1179.36983569136,
            1179.36983569136,
            1179.36983569136,
            1179.36983569136,
            1179.36983569136,
            1179.36983569136,
            1179.36983569136,
            1179.36983569136,
            1179.36983569136,
            1179.36983569136,
            1179.36983569136,
            1179.36983569136,
            1179.36983569136,
            1179.36983569136,
            1179.36983569136,
            1179.36983569136,
            1179.36983569136,
            1179.36983569136,
            1179.36983569136,
            1179.36983569136,
            1179.36983569136,
            1179.36983569136,
            1179.36983569136,
            1179.36983569136,
            1179.36983569136,
            1179.36983569136,
            1179.36983569136,
            1179.36983569136,
            1179.36983569136,
            1179.36983569136,
            1179.36983569136,
            1179.36983569136,
            1179.36983569136,
            1179.36983569136,
            1179.36983569136,
            1179.36983569136,
            1179.36983569136,
            1179.36983569136,
            1179.36983569136,
            1179.36983569136,
            1179.36983569136,
            1179.36983569136,
            1179.36983569136,
            1179.36983569136,
            1179.36983569136,
            1179.36983569136,
            1179.36983569136,
            1179.36983569136,
            1179.36983569136,
            1179.36983569136,
            1179.36983569136,
            1179.36983569136,
            1179.36983569136,
            1179.36983569136,
            1179.36983569136,
            1179.36983569136,
            1179.36983569136,
            1179.36983569136,
            1179.36983569136,
            1179.36983569136,
            1179.36983569136,
            1179.36983569136,
            1179.36983569136,
            1179.36983569136,
            1179.36983569136,
            1179.36983569136,
            1179.36983569136,
            1179.36983569136,
            1179.36983569136,
            1179.36983569136,
            1179.36983569136,
            1179.36983569136,
            1179.36983569136,
            1179.36983569136,
            1179.36983569136,
            1179.36983569136,
            1179.36983569136,
            1179.36983569136,
            1179.36983569136,
            1179.36983569136,
            1179.36983569136,
            1179.36983569136,
            1179.36983569136,
            1179.36983569136,
            1179.36983569136,
            1179.36983569136,
            1179.36983569136,
            1179.36983569136,
            1179.36983569136,
            1179.36983569136,
            1179.36983569136,
            1179.36983569136,
            1179.36983569136,
            1179.36983569136,
            1179.36983569136,
            1179.36983569136,
            1179.36983569136,
            1179.36983569136,
            1179.36983569136,
            1179.36983569136,
            1179.36983569136,
            1179.36983569136,
            1179.36983569136,
            1179.36983569136,
            1179.36983569136,
            1179.36983569136,
            1179.36983569136,
            1179.36983569136,
            1179.36983569136,
            1179.36983569136,
            1179.36983569136,
            1179.36983569136,
            1179.36983569136,
            1179.36983569136,
            1179.36983569136,
            1179.36983569136,
            1179.36983569136,
            1179.36983569136,
            1179.36983569136,
            1179.36983569136,
            1179.36983569136,
            1179.36983569136,
            1179.36983569136,
            1179.36983569136,
            1179.36983569136,
            1179.36983569136,
            1179.36983569136,
            1179.36983569136,
            1179.36983569136,
            1179.36983569136,
            1179.36983569136,
            1179.36983569136,
            1179.36983569136,
            1179.36983569136,
            1179.36983569136,
            1179.36983569136,
            1179.36983569136,
            1179.36983569136,
            1179.36983569136,
            1179.36983569136,
            1179.36983569136,
            1179.36983569136,
            1179.36983569136,
            1179.36983569136,
            1179.36983569136,
            1179.36983569136,
            1179.36983569136,
            1179.36983569136,
            1179.36983569136,
            1179.36983569136,
            1179.36983569136,
            1179.36983569136,
            1179.36983569136,
            1179.36983569136,
            1179.36983569136,
            1179.36983569136,
            1179.36983569136,
            1179.36983569136,
            1179.36983569136,
            1179.36983569136,
            1179.36983569136,
            1179.36983569136,
            1179.36983569136,
            1179.36983569136,
            1179.36983569136,
            1179.36983569136,
            1179.36983569136,
            1179.36983569136,
            1179.36983569136,
            1179.36983569136,
            1179.36983569136,
            1179.36983569136,
            1179.36983569136,
            1179.36983569136,
            1179.36983569136,
            1179.36983569136,
            1179.36983569136,
            1179.36983569136,
            1179.36983569136,
            1179.36983569136,
            1179.36983569136,
            1179.36983569136,
            1179.36983569136,
            1179.36983569136,
            1179.36983569136,
            1179.36983569136,
            1179.36983569136,
            1179.36983569136,
            1179.36983569136,
            1179.36983569136,
            1179.36983569136,
            1179.36983569136,
            1179.36983569136,
            1179.36983569136,
            1179.36983569136,
            1179.36983569136,
            1179.36983569136,
            1179.36983569136,
            1179.36983569136,
            1179.36983569136,
            1179.36983569136,
            1179.36983569136,
            1179.36983569136,
            1179.36983569136,
            1179.36983569136,
            1179.36983569136,
            1179.36983569136,
            1179.36983569136,
            1179.36983569136,
            1179.36983569136,
            1179.36983569136,
            1179.36983569136,
            1179.36983569136,
            1179.36983569136,
            1179.36983569136,
            1179.36983569136,
            1179.36983569136,
            1179.36983569136,
            1179.36983569136,
            1179.36983569136,
            1179.36983569136,
            1179.36983569136,
            1179.36983569136,
            1179.36983569136,
            1179.36983569136,
            1179.36983569136,
            1179.36983569136,
            1179.36983569136,
            1179.36983569136,
            1179.36983569136,
            1179.36983569136,
            1179.36983569136,
            1179.36983569136,
            1179.36983569136,
            1179.36983569136,
            1179.36983569136,
            1179.36983569136,
            1179.36983569136,
            1179.36983569136,
            1179.36983569136,
            1179.36983569136,
            1179.36983569136,
            1179.36983569136,
            1179.36983569136,
            1179.36983569136,
            1179.36983569136,
            1179.36983569136,
            1179.36983569136,
            1179.36983569136,
            1179.36983569136,
            1179.36983569136,
            1179.36983569136,
            1179.36983569136,
            1179.36983569136,
            1179.36983569136,
            1179.36983569136,
            1179.36983569136,
            1179.36983569136,
            1179.36983569136,
            1179.36983569136,
            1179.36983569136,
            1179.36983569136,
            1179.36983569136,
            1179.36983569136,
            1179.36983569136,
            1179.36983569136,
            1179.36983569136,
            1179.36983569136,
            1179.36983569136,
            1179.36983569136,
            1179.36983569136,
            1179.36983569136,
            1179.36983569136,
            1179.36983569136,
            1179.36983569136,
            1179.36983569136,
            1179.36983569136,
            1179.36983569136,
            1179.36983569136,
            1179.36983569136,
            1179.36983569136,
            1179.36983569136,
            1179.36983569136,
            1179.36983569136,
            1179.36983569136,
            1179.36983569136,
            1179.36983569136,
            1179.36983569136,
            1179.36983569136,
            1179.36983569136,
            1179.36983569136,
            1179.36983569136,
            1179.36983569136,
            1179.36983569136,
            1179.36983569136,
            1179.36983569136,
            1179.36983569136,
            1179.36983569136,
            1179.36983569136,
            1179.36983569136,
            1179.36983569136,
            1179.36983569136,
            1179.36983569136,
            1179.36983569136,
            1179.36983569136,
            1179.36983569136,
            1179.36983569136,
            1179.36983569136,
            1179.36983569136,
            1179.36983569136,
            1179.36983569136,
            1179.36983569136,
            1179.36983569136,
            1179.36983569136,
            1179.36983569136,
            1179.36983569136,
            1179.36983569136,
            1179.36983569136,
            1179.36983569136,
            1179.36983569136,
            1179.36983569136,
            1179.36983569136,
            1179.36983569136,
            1179.36983569136,
            1179.36983569136,
            1179.36983569136,
            1179.36983569136,
            1179.36983569136,
            1179.36983569136,
            1179.36983569136,
            1179.36983569136,
            1179.36983569136,
            1179.36983569136,
            1179.36983569136,
            1179.36983569136,
            1179.36983569136,
            1179.36983569136,
            1179.36983569136,
            1179.36983569136,
            1179.36983569136,
            1179.36983569136,
            1179.36983569136,
            1179.36983569136,
            1179.36983569136,
            1179.36983569136,
            1179.36983569136,
            1179.36983569136,
            1179.36983569136,
            1179.36983569136,
            1179.36983569136,
            1179.36983569136,
            1179.36983569136,
            1179.36983569136,
            1179.36983569136,
            1179.36983569136,
            1179.36983569136,
            1179.36983569136,
            1179.36983569136,
            1179.36983569136,
            1179.36983569136,
            1179.36983569136,
            1179.36983569136,
            1179.36983569136,
            1179.36983569136,
            1179.36983569136,
            1179.36983569136,
            1179.36983569136,
            1179.36983569136,
            1179.36983569136,
            1179.36983569136,
            1179.36983569136,
            1179.36983569136,
            1179.36983569136,
            1179.36983569136,
            1179.36983569136,
            1179.36983569136,
            1179.36983569136,
            1179.36983569136,
            1179.36983569136,
            1179.36983569136,
            1179.36983569136,
            1179.36983569136,
            1179.36983569136,
            1179.36983569136,
            1179.36983569136,
            1179.36983569136,
            1179.36983569136,
            1179.36983569136,
            1179.36983569136,
            1179.36983569136,
            1179.36983569136,
            1179.36983569136,
            1179.36983569136,
            1179.36983569136,
            1179.36983569136,
            1179.36983569136,
            1179.36983569136,
            1179.36983569136,
            1179.36983569136,
            1179.36983569136,
            1179.36983569136,
            1179.36983569136,
            1179.36983569136,
            1179.36983569136,
            1179.36983569136,
            1179.36983569136,
            1179.36983569136,
            1179.36983569136,
            1179.36983569136,
            1179.36983569136,
            1179.36983569136,
            1179.36983569136,
            1179.36983569136,
            1179.36983569136,
            1179.36983569136,
            1179.36983569136,
            1179.36983569136,
            1179.36983569136,
            1179.36983569136,
            1179.36983569136,
            1179.36983569136,
            1179.36983569136,
            1179.36983569136,
            1179.36983569136,
            1179.36983569136,
            1179.36983569136,
            1179.36983569136,
            1179.36983569136,
            1179.36983569136,
            1179.36983569136,
            1179.36983569136,
            1179.36983569136,
            1179.36983569136,
            1179.36983569136,
            1179.36983569136,
            1179.36983569136,
            1179.36983569136,
            1179.36983569136,
            1179.36983569136,
            1179.36983569136,
            1179.36983569136,
            1179.36983569136,
            1179.36983569136,
            1179.36983569136,
            1179.36983569136,
            1179.36983569136,
            1179.36983569136,
            1179.36983569136,
            1179.36983569136,
            1179.36983569136,
            1179.36983569136,
            1179.36983569136,
            1179.36983569136,
            1179.36983569136,
            1179.36983569136,
            1179.36983569136,
            1179.36983569136,
            1179.36983569136,
            1179.36983569136,
            1179.36983569136,
            1179.36983569136,
            1179.36983569136,
            1179.36983569136,
            1179.36983569136,
            1179.36983569136,
            1179.36983569136,
            1179.36983569136,
            1179.36983569136,
            1179.36983569136,
            1179.36983569136,
            1179.36983569136,
            1179.36983569136,
            1179.36983569136,
            1179.36983569136,
            1179.36983569136,
            1179.36983569136,
            1179.36983569136,
            1179.36983569136,
            1179.36983569136,
            1179.36983569136,
            1179.36983569136,
            1179.36983569136,
            1179.36983569136,
            1179.36983569136,
            1179.36983569136,
            1179.36983569136,
            1179.36983569136,
            1179.36983569136,
            1179.36983569136,
            1179.36983569136,
            1179.36983569136,
            1179.36983569136,
            1179.36983569136,
            1179.36983569136,
            1179.36983569136,
            1179.36983569136,
            1179.36983569136,
            1179.36983569136,
            1179.36983569136,
            1179.36983569136,
            1179.36983569136,
            1179.36983569136,
            1179.36983569136,
            1179.36983569136,
            1179.36983569136,
            1179.36983569136,
            1179.36983569136,
            1179.36983569136,
            1179.36983569136,
            1179.36983569136,
            1179.36983569136
        ],
        "time_stamps_s": [
            78.4396653000731,
            78.76754920021631,
            79.03276400011964,
            79.36007790011354,
            79.58886890020221,
            79.86843770020641,
            80.1091696000658,
            80.3889982001856,
            80.75222220015712,
            81.09597230004147,
            81.35408540023491,
            81.71950830006972,
            82.00949700013734,
            82.32759220013395,
            82.51928220014088,
            82.78000560007058,
            83.02275770017877,
            83.28592450008728,
            83.53022050019354,
            83.85270580020733,
            84.09142920002341,
            84.3682633000426,
            84.70338340010494,
            84.98833800014108,
            85.32968850014731,
            85.64073920017108,
            85.9752420000732,
            86.23662220011465,
            86.49432120006531,
            86.78775910008699,
            87.06573560019024,
            87.33102070004679,
            87.59588900022209,
            87.89234080002643,
            88.18755730008706,
            88.49901000014506,
            88.77367050014436,
            89.01067640003748,
            89.32923970022239,
            89.61197790014558,
            89.84322410007007,
            90.07363710016944,
            90.30049880011939,
            90.51418590010144,
            90.8525185000617,
            91.13530000019819,
            91.38177610002458,
            91.69662190019153,
            91.90486920019612,
            92.16470100008883,
            92.37319940002635,
            92.61960060009733,
            92.90275890007615,
            93.15030480013229,
            93.37627250002697,
            93.64582500024699,
            93.95310440007597,
            94.23861870006658,
            94.4705552002415,
            94.77935660001822,
            95.0847334000282,
            95.40049800020643,
            95.64251390006393,
            95.91564430017024,
            96.24686330021359,
            96.54369490011595,
            96.86983530013822,
            97.09229490021244,
            97.37321710004471,
            97.59492460009642,
            97.8836425000336,
            98.1936272000894,
            98.46988740004599,
            98.7424069000408,
            98.97006300021894,
            99.21708350023255,
            99.52863630023785,
            99.7630903001409,
            100.01299590012059,
            100.33342080004513,
            100.65844730008394,
            100.91698690014891,
            101.23417450021952,
            101.46652000024915,
            101.67338980012573,
            101.9986694001127,
            102.26926400023513,
            102.58698970009573,
            102.89713260019198,
            103.14664890011773,
            103.35973110003397,
            103.69632090022787,
            103.94802000024356,
            104.23268310003914,
            104.4787615002133,
            104.81369830016047,
            105.12858610018156,
            105.43699930002913,
            105.68618400022388,
            106.04687030008063,
            106.37561310012825,
            106.60251230024733,
            106.81304730009288,
            107.0975549002178,
            107.34774800017476,
            107.69811010011472,
            107.91905460017733,
            108.24996190005913,
            108.55718810018152,
            108.77330720005557,
            109.05055790022016,
            109.36922550015152,
            109.64920740015805,
            109.96948960004374,
            110.28041560016572,
            110.58800180023536,
            110.94566910015419,
            111.2790294000879,
            111.55329680023715,
            111.84960260009393,
            112.17707120021805,
            112.40329970023595,
            112.60728430002928,
            112.93874420016073,
            113.23458690010011,
            113.43527350015938,
            113.72624290012754,
            113.9392938001547,
            114.21988070011139,
            114.53378610010259,
            114.78649200010113,
            115.10128890024498,
            115.36011150013655,
            115.64475010009483,
            115.86728220013902,
            116.17015500017442,
            116.4130336001981,
            116.72992740012705,
            116.97426340007223,
            117.2352402000688,
            117.46577730006538,
            117.78829030017368,
            118.04522920004092,
            118.33874870021828,
            118.5681783000473,
            118.87306650006212,
            119.210197100183,
            119.50282320007682,
            119.82999770017341,
            120.14998280024156,
            120.45949920010753,
            120.75013170018792,
            121.0187911002431,
            121.36139820003882,
            121.62721620011143,
            121.94376320019364,
            122.25993610010482,
            122.65709430002607,
            123.04483640007675,
            123.4426148000639,
            123.88696510018781,
            124.33329630014487,
            124.70537920016795,
            125.17431440018117,
            125.62488330015913,
            125.9347718001809,
            126.28900410002097,
            126.61867820005864,
            126.84840500005521,
            127.07787140016444,
            127.34923740010709,
            127.67362320004031,
            128.01376550015993,
            128.33720990014262,
            128.56152560003102,
            128.8686473001726,
            129.14285250008106,
            129.42924340022728,
            129.66645040013827,
            129.97163030016236,
            130.2297301001381,
            130.52852710010484,
            130.77990780002438,
            131.1472078000661,
            131.4610886001028,
            131.7945341002196,
            131.99386630021036,
            132.26993470010348,
            132.55045900004916,
            132.89179590018466,
            133.19283410022035,
            133.45929890009575,
            133.72012630011886,
            133.99138060002588,
            134.30541340005584,
            134.6022601001896,
            134.80544160003774,
            135.1107018000912,
            135.37373270024545,
            135.65693070017733,
            135.85808500018902,
            136.1017392000649,
            136.29179150005803,
            136.530466100201,
            136.79667700012214,
            137.03695060010068,
            137.29001480014995,
            137.65151990018785,
            137.95619760011323,
            138.2157312000636,
            138.48445360013284,
            138.75763750006445,
            139.07691590022296,
            139.37997480016202,
            139.63917160010897,
            139.92555850022472,
            140.14130930020474,
            140.39256050018594,
            140.68794050021097,
            140.98423570021987,
            141.29855230008252,
            141.59876940003596,
            141.79375700023957,
            142.10994970006868,
            142.32997730001807,
            142.63259580009617,
            142.9338362000417,
            143.21811650018208,
            143.4606398001779,
            143.7501289001666,
            144.02706810017116,
            144.31620960007422,
            144.6319520000834,
            144.90583290020004,
            145.24561090022326,
            145.5886047000531,
            145.89793110010214,
            146.20251580001786,
            146.46852050023153,
            146.82289540022612,
            147.06657060002908,
            147.39739630022086,
            147.6845578001812,
            147.89197060023434,
            148.1688107000664,
            148.36080930009484,
            148.5752281001769,
            148.86682400014251,
            149.0973751002457,
            149.34126270003617,
            149.6826241002418,
            149.97636240022257,
            150.1960013001226,
            150.50390180014074,
            150.80311310011894,
            151.08566270023584,
            151.3274291001726,
            151.65839360002428,
            151.9611802001018,
            152.21398270013742,
            152.49247610010207,
            152.73429020005278,
            153.00340040004812,
            153.24158690008335,
            153.5430503000971,
            153.84756440017372,
            154.06009160005488,
            154.30641100020148,
            154.57560640014708,
            154.9228424001485,
            155.14846440008841,
            155.4463475001976,
            155.68757340009324,
            155.97166940011084,
            156.33517950004898,
            156.70038660010323,
            157.03389920014888,
            157.29191250004806,
            157.57052040006965,
            157.88502270006575,
            158.1876931001898,
            158.4246579001192,
            158.6973200000357,
            158.97770290006883,
            159.27790100011043,
            159.64980840007775,
            159.90958930016495,
            160.22785600018688,
            160.48416930017993,
            160.88418860011734,
            161.2827902000863,
            161.63523070001975,
            161.9590486001689,
            162.28271090006456,
            162.65919990022667,
            163.09184510004707,
            163.5016872000415,
            163.9500027000904,
            164.31628580018878,
            164.71542170015164,
            165.0447227000259,
            165.34435010002926,
            165.7352019001264,
            166.02705440018326,
            166.40138400020078,
            166.76103120017797,
            167.04670090018772,
            167.365564300213,
            167.64233750011772,
            167.90923320013098,
            168.1903564000968,
            168.5342427000869,
            168.92182190017775,
            169.20080440002494,
            169.4332471000962,
            169.72497630002908,
            170.0598251002375,
            170.32827500021085,
            170.57263110019267,
            170.86845620023087,
            171.1239398000762,
            171.40299690002576,
            171.72489420021884,
            172.047997900052,
            172.34618390002288,
            172.67703780019656,
            172.91217550006695,
            173.20525670005009,
            173.5113302001264,
            173.76055810018443,
            174.0981378001161,
            174.32112870016135,
            174.58800550014712,
            174.9697935001459,
            175.21041430020705,
            175.56634770007804,
            175.88697770005092,
            176.20748990005814,
            176.53954130015336,
            176.89002650021575,
            177.17048870003782,
            177.46506790001877,
            177.7744236001745,
            178.04460070002824,
            178.33506660023704,
            178.65767040010542,
            179.00915130018257,
            179.24938370008022,
            179.44659500010312,
            179.75647640018724,
            180.02786690020002,
            180.3127942001447,
            180.5338153000921,
            180.81097370013595,
            181.1159040001221,
            181.33100780006498,
            181.63783280015923,
            182.0034375002142,
            182.28609010018408,
            182.55596300004981,
            182.86838120012544,
            183.11006110021845,
            183.35847740015015,
            183.66468750010245,
            183.94208320020698,
            184.2417454002425,
            184.4989305001218,
            185.0027935001999,
            185.39454330014996,
            185.71426880010404,
            185.96246240008622,
            186.3524658002425,
            186.5727720002178,
            186.90924660023302,
            187.21088900021277,
            187.51650520018302,
            187.84288840019144,
            188.09262390015647,
            188.4444052001927,
            188.74144170014188,
            189.0052770001348,
            189.31646700017154,
            189.66778540005907,
            189.95067070005462,
            190.1695194002241,
            190.3925696001388,
            190.62857260019518,
            190.88059300021268,
            191.17658890015446,
            191.43796300003305,
            191.7472979000304,
            192.0846206001006,
            192.37565290019847,
            192.64261060021818,
            192.9495049000252,
            193.24031520006247,
            193.45835200021975,
            193.65810680016875,
            193.93898890004493,
            194.17538120015524,
            194.4811330002267,
            194.69111070013605,
            194.97262900019996,
            195.24784580012783,
            195.58218340016901,
            195.8518738001585,
            196.1695178002119,
            196.49159060022794,
            196.6830766000785,
            196.90194080024958,
            197.15341460006312,
            197.48022710019723,
            197.76892850012518,
            198.03093210002407,
            198.36875570006669,
            198.74523030011915,
            199.093608800089,
            199.4270190000534,
            199.68780110008083,
            199.9498837001156,
            200.1896638001781,
            200.47514660004526,
            200.75101290014572,
            201.03239860013127,
            201.28386140009388,
            201.69512820011005,
            202.0233074000571,
            202.2731260000728,
            202.62467500008643,
            202.87645700015128,
            203.19861940015107,
            203.4444784000516,
            203.74914970016107,
            203.94489000015892,
            204.23210340016522,
            204.60805360018276,
            204.86321570002474,
            205.18553300015628,
            205.47047150018625,
            205.81615360011347,
            206.08617680007592,
            206.3513463002164,
            206.6764690000564,
            206.94642670010217,
            207.2350270000752,
            207.49019790021703,
            207.7710229002405,
            208.01845280011185,
            208.29065980017185,
            208.5915949002374,
            208.87861690018326,
            209.13607290014625,
            209.42644450021908,
            209.70975320017897,
            210.03801450016908,
            210.38506250013597,
            210.67421400011517,
            210.94226980023086,
            211.15885850018822,
            211.44821660011075,
            211.70520430011675,
            211.91944370022975,
            212.23128320020624,
            212.51562250009738,
            212.8447919001337,
            213.1101101001259,
            213.49308760021813,
            213.7754326001741,
            214.16015130002052,
            214.50561160012148,
            214.87829370005056,
            215.14003600017168,
            215.52889480022714,
            215.9260666000191,
            216.25773460022174,
            216.45458960020915,
            216.92147940024734,
            217.17825300013646,
            217.4187411002349,
            217.7354154002387,
            217.94808990019374,
            218.19787410018034,
            218.40866120019928,
            218.66971050016582,
            218.97227590018883,
            219.1999649000354,
            219.45056350016966,
            219.7911528002005,
            220.12139630015008,
            220.4138786001131,
            220.6614577001892,
            220.99369840021245,
            221.23994680005126,
            221.66232590004802,
            221.97930190013722,
            222.3088362000417,
            222.69751430023462,
            223.07610120018944,
            223.4074896001257,
            223.7578891001176,
            224.03882310003974,
            224.27212570002303,
            224.6215196000412,
            224.99672810011543,
            225.42336200014688,
            225.8952366001904,
            226.40588590013795,
            226.71308610006236,
            226.93875780003145,
            227.31118140020408,
            227.62332470016554,
            227.91578010004014,
            228.231541500194,
            228.5957296001725
        ]
    },
    "price": [
        37.71,
        37.71,
        37.71,
        37.71,
        32.4,
        32.4,
        32.4,
        32.4,
        31.7,
        31.7,
        31.7,
        31.7,
        30.55,
        30.55,
        30.55,
        30.55,
        30.55,
        30.55,
        30.55,
        30.55,
        31.87,
        31.87,
        31.87,
        31.87,
        39.84,
        39.84,
        39.84,
        39.84,
        43.21,
        43.21,
        43.21,
        43.21,
        44.07,
        44.07,
        44.07,
        44.07,
        43.37,
        43.37,
        43.37,
        43.37,
        37.27,
        37.27,
        37.27,
        37.27,
        37.0,
        37.0,
        37.0,
        37.0,
        41.31,
        41.31,
        41.31,
        41.31,
        44.3,
        44.3,
        44.3,
        44.3,
        45.26,
        45.26,
        45.26,
        45.26,
        44.51,
        44.51,
        44.51,
        44.51,
        45.57,
        45.57,
        45.57,
        45.57,
        44.35,
        44.35,
        44.35,
        44.35,
        45.0,
        45.0,
        45.0,
        45.0,
        48.69,
        48.69,
        48.69,
        48.69,
        51.57,
        51.57,
        51.57,
        51.57,
        52.26,
        52.26,
        52.26,
        52.26,
        49.24,
        49.24,
        49.24,
        49.24,
        45.26,
        45.26,
        45.26,
        45.26,
        42.11,
        42.11,
        42.11
    ],
    "solution_datetime": "2024-06-02 00:50",
    "solver": "PSO-RBO"
}