{
    "configuration": {
        "action_type": "exiting_flows",
        "activation_fn_name": null,
        "actor_layers": null,
        "algorithm": "SAC",
        "checkpoint_callback": false,
        "checkpoint_timesteps_freq": null,
        "critic_layers": null,
        "dam_ids": [
            "dam1",
            "dam2"
        ],
        "discretization_levels": null,
        "do_history_updates": false,
        "evaluation_callback": true,
        "evaluation_num_episodes": 10,
        "evaluation_save_best": true,
        "evaluation_timesteps_freq": 495,
        "feature_extractor": "MLP",
        "features": [
            "past_vols",
            "past_flows",
            "past_variations",
            "future_prices",
            "future_inflows",
            "past_turbined",
            "past_groups",
            "past_powers",
            "past_clipped"
        ],
        "features_not_expand": [],
        "flow_smoothing": 2,
        "flow_smoothing_clip": false,
        "flow_smoothing_penalty": 25.0,
        "greediness": 1.0,
        "greedy_reference": false,
        "hyperparams": null,
        "learning_rate": 0.001,
        "length_episodes": 99,
        "limit_zones_penalty": 50,
        "log_episode_freq": 5,
        "log_std_init": null,
        "lr_schedule_name": null,
        "max_iterations": 20,
        "milp_intercept": null,
        "milp_reference": false,
        "milp_slope": null,
        "mode": "linear",
        "noise_std_dev": 0.0,
        "normalization": false,
        "num_actions_block": 1,
        "num_dams": 6,
        "num_steps_sight": [
            {
                "key": [
                    "past_vols",
                    "dam1"
                ],
                "value": 1
            },
            {
                "key": [
                    "past_vols",
                    "dam2"
                ],
                "value": 1
            },
            {
                "key": [
                    "past_flows",
                    "dam1"
                ],
                "value": 2
            },
            {
                "key": [
                    "past_flows",
                    "dam2"
                ],
                "value": 6
            },
            {
                "key": [
                    "past_variations",
                    "dam1"
                ],
                "value": 2
            },
            {
                "key": [
                    "past_variations",
                    "dam2"
                ],
                "value": 2
            },
            {
                "key": [
                    "future_prices",
                    "dam1"
                ],
                "value": 16
            },
            {
                "key": [
                    "future_prices",
                    "dam2"
                ],
                "value": 16
            },
            {
                "key": [
                    "future_inflows",
                    "dam1"
                ],
                "value": 16
            },
            {
                "key": [
                    "future_inflows",
                    "dam2"
                ],
                "value": 16
            },
            {
                "key": [
                    "past_turbined",
                    "dam1"
                ],
                "value": 1
            },
            {
                "key": [
                    "past_turbined",
                    "dam2"
                ],
                "value": 1
            },
            {
                "key": [
                    "past_groups",
                    "dam1"
                ],
                "value": 1
            },
            {
                "key": [
                    "past_groups",
                    "dam2"
                ],
                "value": 1
            },
            {
                "key": [
                    "past_powers",
                    "dam1"
                ],
                "value": 1
            },
            {
                "key": [
                    "past_powers",
                    "dam2"
                ],
                "value": 1
            },
            {
                "key": [
                    "past_clipped",
                    "dam1"
                ],
                "value": 1
            },
            {
                "key": [
                    "past_clipped",
                    "dam2"
                ],
                "value": 1
            }
        ],
        "num_timesteps": 99000,
        "obs_random": false,
        "obs_random_features_excluded": [],
        "optimal_flow_values": {},
        "ortho_init": null,
        "projector_bound": null,
        "projector_explained_variance": null,
        "projector_extrapolation": null,
        "projector_type": "identity",
        "random_intercept": null,
        "random_reference": false,
        "random_slope": null,
        "randomness": false,
        "recalculate_reference": false,
        "reference_num_periods": null,
        "reference_ratio": null,
        "replay_buffer_size": null,
        "startups_penalty": 50,
        "training_data_callback": true,
        "training_data_instances": [
            "Percentile00",
            "Percentile10",
            "Percentile20",
            "Percentile30",
            "Percentile40",
            "Percentile50",
            "Percentile60",
            "Percentile70",
            "Percentile80",
            "Percentile90",
            "Percentile100"
        ],
        "training_data_timesteps_freq": 495,
        "unique_features": [
            "future_prices"
        ],
        "use_sde": false,
        "volume_exceedance_bonus": 0.0,
        "volume_objectives": {},
        "volume_shortage_penalty": 0.0
    },
    "dams": [
        {
            "flows": [
                1.8920799538493156,
                13.595531582832336,
                3.925470006465912,
                2.8757214812364125,
                1.7034046535873009,
                1.712351700603176,
                1.6964084231111094,
                1.6335473231111084,
                0.052007348835468294,
                3.3985434911645362,
                1.7403900320317431,
                1.7238908248888927,
                1.6803899908888869,
                1.7389201909523804,
                1.729865755365083,
                1.722070816920637,
                1.7203724100952402,
                1.7240798434920646,
                1.7020536982857124,
                1.737501460380954,
                1.6920875934920656,
                1.7040569630793632,
                1.7319318396190486,
                1.716747556285716,
                1.7051153807936499,
                1.6963439631111072,
                1.7159051478412666,
                1.7024596286349212,
                1.7113567988571432,
                1.7176611234603156,
                1.7180896997142878,
                1.647617126253972,
                1.6782166049206313,
                1.6578783498095273,
                1.6720297885396818,
                1.7298416352698405,
                1.714823571492064,
                1.7378104527301588,
                1.6869654429206355,
                1.6973863934920599,
                1.66596828949206,
                1.6988237774603152,
                1.7072458550476182,
                1.6968371149841308,
                1.7128315879365092,
                2.580083440126982,
                2.931747733650797,
                2.8906866633968216,
                3.1371826784761896,
                2.8707100020000023,
                2.2725589880634893,
                1.6809166954603199,
                1.6564823218412736,
                1.6323007459999967,
                2.1261874740000026,
                2.1702959631746004,
                0.1679743707180023,
                0.2463693544268608,
                6.547470180759896,
                1.8676223319682563,
                1.791240357269837,
                1.7077194470476227,
                1.7032124295873008,
                1.696498660888885,
                1.6869841341269864,
                1.6838683684761862,
                1.6907474256825419,
                1.5364031431428562,
                1.6427135031746003,
                0.9888307988643646,
                2.3952198919610317,
                1.6571246802539665,
                1.672654112222226,
                1.639096602571428,
                1.6368245018412724,
                1.6546090500317465,
                1.666723442507937,
                1.6651159430476157,
                1.6630427401587318,
                1.6749346199047592,
                1.6236842321269878,
                1.593728722063493,
                1.6156370469206336,
                1.6375619721269807,
                1.6634555410158727,
                1.6799783630158749,
                0.69526277333498,
                0.5136475801467896,
                3.794862762232523,
                1.6680051713015887,
                1.675285006253972,
                1.6755757881269853,
                1.6533720531111127,
                1.6606628100000025,
                1.6684271211111141,
                1.6172711679047642,
                1.6206767426984152,
                1.6669757555555569,
                1.6550370758412707
            ],
            "id": "dam1",
            "objective_function_details": {
                "income_from_energy_eur": 184.5326718673015,
                "limit_zones": 1.0,
                "startups": 5.0,
                "total_income_eur": -115.4673281326985
            },
            "power": [
                1.1194685676127278,
                0.13297264858973115,
                4.581537213862782,
                1.1113904208276009,
                0.43585780505491367,
                0.07867759815461899,
                0.08125228794336006,
                0.07666429442046317,
                0.05857476924060676,
                0.0,
                0.772303450332734,
                0.08932087252712036,
                0.08457289924860224,
                0.07205467363708977,
                0.08889789667694402,
                0.08629230370218216,
                0.08404915594838475,
                0.08356040578280297,
                0.08462729309124163,
                0.07828883403905396,
                0.0884896288866055,
                0.07542089021354409,
                0.07886531311636354,
                0.08688686032202841,
                0.08251728238437872,
                0.07916989375356834,
                0.07664574478017477,
                0.08227486268813429,
                0.0784056485280349,
                0.08096598528263117,
                0.0827801794130405,
                0.0829035107091476,
                0.06262363345438048,
                0.07142923882608097,
                0.06557650354231004,
                0.06964886001141923,
                0.08628536266758002,
                0.08196361769555804,
                0.08857854754824716,
                0.07394689004910378,
                0.07694572474591654,
                0.06790454373872233,
                0.07735936042023463,
                0.07978297986981821,
                0.07678765898823911,
                0.08139038501770053,
                0.3309592633458942,
                0.47191173600676306,
                0.4454881769081399,
                0.6041129273527333,
                0.4326328253611127,
                0.24246301814776677,
                0.0722062432979338,
                0.06517476887518668,
                0.05821604201438758,
                0.20034171913669147,
                0.21303480954664764,
                0.0,
                0.0,
                2.2151309808141186,
                0.12593448401964213,
                0.10395405964599629,
                0.07991926533744541,
                0.07862228189562616,
                0.07669026212629787,
                0.07395226881352131,
                0.07305564560465791,
                0.0750352304122423,
                0.030619609537512596,
                0.06121251889916558,
                0.0,
                0.27776111998878616,
                0.06535962021696881,
                0.06982852150279889,
                0.06017168419321671,
                0.05951784225648128,
                0.06463569785086233,
                0.06812185395911856,
                0.06765926418636425,
                0.06706265903848399,
                0.07048478270640555,
                0.05573646967683103,
                0.047116179011077154,
                0.05342073292680106,
                0.05973006392143333,
                0.06718145065204972,
                0.07193621957291367,
                0.0,
                0.0,
                1.027342240510744,
                0.0684906967774356,
                0.07058561331049555,
                0.07066929154733392,
                0.06427972751398929,
                0.06637778705036046,
                0.06861212118305446,
                0.05389098356971635,
                0.05487100509306915,
                0.06819446203037612
            ],
            "volume": [
                47874.340129709766,
                37157.477108960666,
                35156.58158962706,
                34045.0,
                34045.0,
                34045.0,
                34045.0,
                34045.0,
                35542.751892362365,
                34045.0,
                34045.0,
                34045.0,
                34045.0,
                34045.0,
                34045.0,
                34045.0,
                34045.0,
                34045.0,
                34045.0,
                34045.0,
                34045.0,
                34045.0,
                34045.0,
                34045.0,
                34045.0,
                34045.0,
                34045.0,
                34045.0,
                34045.0,
                34045.0,
                34045.0,
                34045.0,
                34045.0,
                34045.0,
                34045.0,
                34045.0,
                34045.0,
                34045.0,
                34045.0,
                34045.0,
                34045.0,
                34045.0,
                34045.0,
                34045.0,
                34045.0,
                34045.0,
                34045.0,
                34045.0,
                34045.0,
                34045.0,
                34045.0,
                34045.0,
                34045.0,
                34045.0,
                34045.0,
                34045.0,
                36268.857757953796,
                38018.12086559819,
                34045.0,
                34045.0,
                34045.0,
                34045.0,
                34045.0,
                34045.0,
                34045.0,
                34045.0,
                34045.0,
                34045.0,
                34045.0,
                34678.65448733636,
                34045.0,
                34045.0,
                34045.0,
                34045.0,
                34045.0,
                34045.0,
                34045.0,
                34045.0,
                34045.0,
                34045.0,
                34045.0,
                34045.0,
                34045.0,
                34045.0,
                34045.0,
                34045.0,
                34931.86726539852,
                35969.23656663784,
                34045.0,
                34045.0,
                34045.0,
                34045.0,
                34045.0,
                34045.0,
                34045.0,
                34045.0,
                34045.0,
                34045.0,
                34045.0
            ]
        },
        {
            "flows": [
                1.5069781681895256,
                4.284599813478861,
                3.1265050864219663,
                5.370441890578509,
                5.185597740800675,
                4.890113020311894,
                4.462507178312367,
                4.031410778083304,
                0.04142210751771927,
                3.3035174843711825,
                3.3985434911645362,
                1.7403900320317431,
                1.7238908248888927,
                1.6803899908888869,
                1.7389201909523804,
                1.729865755365083,
                1.722070816920637,
                1.7203724100952402,
                1.7240798434920646,
                1.7020536982857124,
                1.737501460380954,
                1.6920875934920656,
                1.7040569630793632,
                1.7319318396190486,
                1.716747556285716,
                1.7051153807936499,
                1.6963439631111072,
                1.7159051478412666,
                1.7024596286349212,
                1.7113567988571432,
                1.7176611234603156,
                1.7180896997142878,
                1.647617126253972,
                1.6782166049206313,
                1.6578783498095273,
                1.6720297885396818,
                1.7298416352698405,
                1.714823571492064,
                1.7378104527301588,
                1.6869654429206355,
                1.6973863934920599,
                1.66596828949206,
                1.6988237774603152,
                1.7072458550476182,
                1.6968371149841308,
                1.7128315879365092,
                2.580083440126982,
                2.931747733650797,
                2.8906866633968216,
                3.1371826784761896,
                2.8707100020000023,
                2.2725589880634893,
                1.6809166954603199,
                1.6564823218412736,
                1.6323007459999967,
                1.857479589879513,
                0.13378594756126405,
                0.19622492045164108,
                2.5233367044270483,
                1.874331640303135,
                4.137807390783148,
                3.7819480167800066,
                2.119965269179322,
                1.7032124295873008,
                1.696498660888885,
                1.6869841341269864,
                1.6838683684761862,
                1.6907474256825419,
                1.5364031431428562,
                0.7875705373287201,
                1.8439737647102448,
                2.3952198919610317,
                1.6571246802539665,
                1.672654112222226,
                1.639096602571428,
                1.6368245018412724,
                1.6546090500317465,
                1.666723442507937,
                1.6651159430476157,
                1.6630427401587318,
                1.6749346199047592,
                1.6236842321269878,
                1.405413109958172,
                1.803952659025955,
                1.6375619721269807,
                1.6634555410158727,
                0.553753459751606,
                0.4091030550003052,
                1.9260322017457332,
                3.029061851501465,
                2.4338060820326466,
                1.675285006253972,
                1.6755757881269853,
                1.6533720531111127,
                1.5153880715370178,
                1.8137018595740988,
                1.6172711679047642,
                1.6206767426984152,
                1.6669757555555569
            ],
            "id": "dam2",
            "objective_function_details": {
                "income_from_energy_eur": 268.00859578524484,
                "limit_zones": 2.0,
                "startups": 5.0,
                "total_income_eur": -81.99140421475516
            },
            "power": [
                1.6433088180615028,
                1.5830907852557545,
                1.526496235645318,
                0.4944899310296667,
                1.017157767040687,
                0.9158935042784816,
                3.049997274740968,
                3.48,
                3.517651929905975,
                3.48,
                3.382798063324179,
                0.704473559114063,
                0.06426972817512354,
                0.0,
                0.6531634137039316,
                0.0,
                0.0,
                0.0,
                0.0,
                0.0,
                0.0,
                0.0,
                0.0,
                0.0,
                0.0,
                0.0,
                0.0,
                0.0,
                0.0,
                0.0,
                0.0,
                0.0,
                0.0,
                0.0,
                0.0,
                0.0,
                0.0,
                0.0,
                0.0,
                0.0,
                0.0,
                0.0,
                0.0,
                0.0,
                0.0,
                0.0,
                0.0,
                0.0,
                0.0,
                0.0,
                0.0,
                0.6311050910107323,
                0.9388360988607701,
                0.9051200185203313,
                0.5636780645266818,
                0.0,
                0.0,
                0.0,
                0.0,
                0.0,
                0.0,
                0.0,
                0.0,
                0.7045485015216495,
                1.3997814169166178,
                1.535464754772035,
                0.19064087144480485,
                0.0,
                0.0,
                0.0,
                0.0,
                0.0,
                0.0,
                0.0,
                0.0,
                0.0,
                0.0,
                0.0,
                0.0,
                0.0,
                0.0,
                0.0,
                0.0,
                0.0,
                0.0,
                0.0,
                0.0,
                0.0,
                0.0,
                0.0,
                0.0,
                0.0,
                0.0,
                0.0712019794879141,
                0.0,
                0.0,
                0.0,
                0.0,
                0.0
            ],
            "volume": [
                22165.6333636199,
                20012.36548995331,
                29434.489336722643,
                28134.01464102131,
                26055.126007413473,
                23187.08847736134,
                20711.948547423068,
                18610.446427948093,
                20043.359121982143,
                17117.0,
                17117.0,
                17117.0,
                17117.0,
                17117.0,
                17117.0,
                17117.0,
                17117.0,
                17117.0,
                17117.0,
                17117.0,
                17117.0,
                17117.0,
                17117.0,
                17117.0,
                17117.0,
                17117.0,
                17117.0,
                17117.0,
                17117.0,
                17117.0,
                17117.0,
                17117.0,
                17117.0,
                17117.0,
                17117.0,
                17117.0,
                17117.0,
                17117.0,
                17117.0,
                17117.0,
                17117.0,
                17117.0,
                17117.0,
                17117.0,
                17117.0,
                17117.0,
                17117.0,
                17117.0,
                17117.0,
                17117.0,
                17117.0,
                17117.0,
                17117.0,
                17117.0,
                17117.0,
                17358.83709570844,
                19191.696109760444,
                19166.27061500017,
                17117.0,
                21322.824686411084,
                19279.658133477682,
                17488.02123991853,
                17117.0,
                17117.0,
                17117.0,
                17117.0,
                17117.0,
                17117.0,
                17117.0,
                17886.628669261292,
                17117.0,
                17117.0,
                17117.0,
                17117.0,
                17117.0,
                17117.0,
                17117.0,
                17117.0,
                17117.0,
                17117.0,
                17117.0,
                17117.0,
                17286.48405089479,
                17117.0,
                17117.0,
                17117.0,
                18130.602412937842,
                18388.14615943905,
                17117.0,
                17806.220819657952,
                17117.0,
                17117.0,
                17117.0,
                17117.0,
                17247.747264616686,
                17117.0,
                17117.0,
                17117.0,
                17117.0
            ]
        },
        {
            "flows": [
                1.5069781681895256,
                4.202089300135206,
                3.1265050864219663,
                4.1061374538049735,
                3.8886046578505518,
                3.7546113952013185,
                3.6320431900228787,
                3.7305584174026767,
                0.04142210751771927,
                4.6446877302633744,
                4.6704493551257675,
                4.643700070203991,
                4.378150522336727,
                2.0415896010398864,
                3.499058531522751,
                4.002249887214635,
                2.068905077278614,
                3.4541007652889273,
                1.716391979068782,
                1.7302855877460348,
                1.724102994126988,
                1.722174356835979,
                1.7155019839576724,
                1.721211667386245,
                1.7105475840529107,
                1.7112153389841276,
                1.7093587987301604,
                1.7175787863280412,
                1.717931592232805,
                1.706068966730159,
                1.7057881639153412,
                1.704902913195765,
                1.7099071917777757,
                1.7104925169841267,
                1.7157025406772501,
                1.6944559831428585,
                1.6813078102962957,
                1.6612373603280421,
                1.6693749144232788,
                1.686583257873018,
                1.7055649984338621,
                1.7274918864973532,
                1.7131998223809528,
                1.7073874297142861,
                1.6834400419682505,
                1.6873928201481452,
                1.690679307333331,
                1.700968915830688,
                1.705638185989418,
                1.996584047682542,
                2.4082209205714307,
                2.8008392790582004,
                2.9865390251746025,
                2.9661931146243377,
                2.7601505561798936,
                1.857479589879513,
                0.13378594756126405,
                0.19622492045164108,
                3.971750945206489,
                1.874331640303135,
                1.4201479076794445,
                0.9511158574799831,
                1.5312977550606066,
                2.8451585785044435,
                3.2646956826220976,
                3.3465735589141574,
                2.5350419051822084,
                1.8398921198851692,
                1.6955650748677242,
                0.7875705373287201,
                2.5887464932638693,
                1.6370063124338614,
                1.338240368718038,
                1.3893158150606055,
                1.6755880646666668,
                1.9654394456417463,
                1.9083328948124068,
                1.6562917983492056,
                1.6495250722116421,
                1.6435100514814824,
                1.6527189981269839,
                1.6621494785290998,
                1.405413109958172,
                1.9272453663169573,
                1.6538871973968263,
                1.5680106539966396,
                0.553753459751606,
                0.4091030550003052,
                3.760135654728688,
                1.4902474596145636,
                0.875437351922596,
                0.9629629054992135,
                1.7880657027491664,
                2.46296671175995,
                1.5153880715370178,
                2.7922185338635446,
                1.66807761583069,
                1.6147786375917066,
                1.660820661407411
            ],
            "id": "dam3_dam2copy",
            "objective_function_details": {
                "income_from_energy_eur": 314.2774312167227,
                "limit_zones": 2.0,
                "startups": 2.0,
                "total_income_eur": 114.27743121672268
            },
            "power": [
                1.6433088180615028,
                1.5830907852557545,
                1.526496235645318,
                0.4944899310296667,
                0.9715805310984774,
                0.8703162683362713,
                2.3060423499143297,
                2.132879404652329,
                2.4798333656923526,
                2.217952724746053,
                2.1306509919272254,
                0.07955595682580884,
                0.6389215123872259,
                1.158099363700934,
                3.48,
                3.48,
                2.1009479164540488,
                1.468669733182507,
                1.2610293823531604,
                1.2761179311326483,
                1.251284117403489,
                0.0,
                0.0,
                0.0,
                0.0,
                0.0,
                0.0,
                0.0,
                0.0,
                0.0,
                0.0,
                0.0,
                0.0,
                0.0,
                0.0,
                0.0,
                0.0,
                0.0,
                0.0,
                0.0,
                0.0,
                0.0,
                0.0,
                0.0,
                0.0,
                0.0,
                0.0,
                0.0,
                0.0,
                0.0,
                0.0,
                0.0,
                0.0,
                0.0,
                0.0,
                0.5168071908442432,
                0.8250204027972776,
                0.8025447273025941,
                0.17887380113959167,
                0.0,
                0.0,
                0.0,
                0.0,
                0.003441605761581026,
                0.0,
                0.0,
                0.0,
                0.21054111370337716,
                1.2132648910701003,
                1.0419623477111515,
                0.2549279987707521,
                0.0,
                0.0,
                0.0,
                0.0,
                0.0,
                0.0,
                0.0,
                0.0,
                0.0,
                0.0,
                0.0,
                0.0,
                0.0,
                0.0,
                0.0,
                0.0,
                0.0,
                0.0,
                0.0,
                0.0,
                0.0,
                0.0,
                0.0,
                0.0,
                0.0,
                0.0,
                0.0,
                0.0
            ],
            "volume": [
                21691.899261205523,
                20947.80095548998,
                21140.991747069304,
                19892.02722532473,
                19122.704923979607,
                18418.979588725528,
                18984.604754848737,
                19731.865594526673,
                24328.43149326805,
                24509.677917858495,
                24321.482791257575,
                22702.754747248,
                20975.324388136607,
                21160.93867211674,
                20544.5212960165,
                19001.34370194888,
                18682.730386740986,
                17117.0,
                17117.0,
                17117.0,
                17117.0,
                17117.0,
                17117.0,
                17117.0,
                17117.0,
                17117.0,
                17117.0,
                17117.0,
                17117.0,
                17117.0,
                17117.0,
                17117.0,
                17117.0,
                17117.0,
                17117.0,
                17117.0,
                17117.0,
                17117.0,
                17117.0,
                17117.0,
                17117.0,
                17117.0,
                17117.0,
                17117.0,
                17117.0,
                17117.0,
                17117.0,
                17117.0,
                17117.0,
                17117.0,
                17117.0,
                17117.0,
                17117.0,
                17117.0,
                17117.0,
                17492.52407476558,
                19055.104123569967,
                20369.411624153967,
                18338.714570784363,
                17738.885979543775,
                17117.0,
                17117.0,
                17117.0,
                17117.0,
                17117.0,
                17117.0,
                17117.0,
                17117.0,
                17117.0,
                17928.39186545177,
                17117.0,
                17117.0,
                17117.0,
                17117.0,
                17117.0,
                17117.0,
                17117.0,
                17117.0,
                17117.0,
                17117.0,
                17117.0,
                17117.0,
                17350.59283875193,
                17117.0,
                17117.0,
                17117.0,
                18068.53688655689,
                19154.422459389945,
                17301.79142178477,
                17117.0,
                17117.0,
                17117.0,
                17117.0,
                17117.0,
                17894.59661755311,
                17117.0,
                17117.0,
                17117.0,
                17117.0
            ]
        },
        {
            "flows": [
                1.5069781681895256,
                4.202089300135206,
                3.1265050864219663,
                4.1061374538049735,
                3.8886046578505518,
                3.7503001255813757,
                3.6240964572341707,
                3.653484725829694,
                0.04142210751771927,
                4.269310578954695,
                4.189226670952877,
                4.113438094412377,
                3.8555112109174416,
                2.0415896010398864,
                3.499058531522751,
                4.040667702130054,
                2.068905077278614,
                4.376487014399625,
                3.7223967331647874,
                3.1064360523223877,
                4.136965147715091,
                3.986187139844656,
                1.9858935979008674,
                3.7888833269668893,
                2.1074280796717155,
                1.7205931116402118,
                1.7196293360599642,
                1.7157537451322746,
                1.7143248634744264,
                1.7103739072557316,
                1.7127176413474445,
                1.7149563924303342,
                1.7138597817636683,
                1.7099295742927683,
                1.7055866812804217,
                1.7068660896296286,
                1.7084342073192238,
                1.7120340831463827,
                1.7068836802680785,
                1.6971554447054666,
                1.6790003845890653,
                1.6706400283492056,
                1.672398510874781,
                1.687174390243385,
                1.706546714268079,
                1.7154189024373894,
                1.7160263795308655,
                1.7013424313544965,
                1.692740097276894,
                1.6871707231499102,
                1.6930136811040535,
                1.6990954697178111,
                1.8010637165008827,
                2.036814384747797,
                2.401881415770723,
                1.857479589879513,
                0.13378594756126405,
                0.19622492045164108,
                4.403251949762893,
                1.874331640303135,
                4.063749473806852,
                2.3000247999201786,
                2.014102501987088,
                2.422076831063023,
                1.4151984684875223,
                1.3008538400733434,
                1.7758573970150124,
                2.547050672062384,
                3.152142606680233,
                0.7875705373287201,
                3.759727643055877,
                3.098807763160435,
                1.441009244027203,
                1.6906273684867725,
                1.6711077810088157,
                1.8546643914719243,
                1.4548541654041685,
                1.4677147494817715,
                1.6767811084563395,
                1.7754713606834411,
                1.9176701539579517,
                1.738049921791086,
                1.405413109958172,
                1.892947237995977,
                1.6527928427125234,
                1.5734271955380852,
                0.553753459751606,
                0.4091030550003052,
                3.7758828928676467,
                1.5633099781576676,
                0.8436223895828516,
                1.574330723160201,
                1.8864953897811858,
                2.041940155421948,
                1.1095492390121258,
                1.2088219867236574,
                1.7379984400027753,
                1.9221401620153766,
                2.2568577723868373
            ],
            "id": "dam4_dam2copy",
            "objective_function_details": {
                "income_from_energy_eur": 393.2551814816945,
                "limit_zones": 0.0,
                "startups": 3.0,
                "total_income_eur": 243.25518148169448
            },
            "power": [
                1.6433088180615028,
                1.5830907852557545,
                1.526496235645318,
                0.4944899310296667,
                0.9715805310984774,
                0.8703162683362713,
                2.3060423499143297,
                2.132879404652329,
                2.4774519024737174,
                2.2111816377012734,
                2.081305865727847,
                0.032592293845065845,
                0.3889962848906882,
                0.6849299307682568,
                2.9342339997195914,
                2.7056591107085377,
                1.519345300661361,
                1.1799737325889963,
                1.282250651544535,
                1.2973392003240216,
                1.7820139813417235,
                1.6062071603894816,
                2.1793195085088994,
                2.0470121916736335,
                2.192724987744418,
                1.5737586795877676,
                1.381484911936381,
                0.3436941929837082,
                0.19714725771591843,
                0.0,
                0.0,
                0.0,
                0.0,
                0.0,
                0.0,
                0.0,
                0.0,
                0.0,
                0.0,
                0.0,
                0.0,
                0.0,
                0.0,
                0.0,
                0.0,
                0.0,
                0.0,
                0.0,
                0.0,
                0.0,
                0.0,
                0.0,
                0.0,
                0.0,
                0.0,
                0.0,
                0.0,
                0.0,
                0.0,
                0.0,
                0.0,
                0.0,
                0.0,
                1.70206969242502,
                0.5402870763214254,
                0.6174938380135128,
                0.0,
                0.0,
                0.0,
                0.0,
                0.0,
                0.11878989708516734,
                0.0,
                0.2427387204739064,
                0.21327756881535082,
                0.5742246639440372,
                0.0,
                0.0,
                0.0,
                0.0,
                0.0,
                0.0,
                0.0,
                0.0,
                0.0,
                0.0,
                0.0,
                0.0,
                0.0,
                0.0,
                0.0,
                0.0,
                0.0,
                0.0,
                0.0,
                0.0,
                0.0,
                0.0,
                0.0
            ],
            "volume": [
                21691.899261205523,
                20947.80095548998,
                21140.991747069304,
                19892.02722532473,
                19097.951769976513,
                18373.353423377284,
                18542.086163975175,
                18590.3240701517,
                22077.850225442806,
                21618.048477306005,
                21182.90837423648,
                19702.02120374832,
                18757.061590477755,
                19726.598707413916,
                20765.09717572138,
                21236.186228104278,
                22693.203716627708,
                21730.005000137855,
                21242.71734622273,
                21317.98894793738,
                20452.29703392845,
                19036.54795455916,
                19319.4772160795,
                17460.716390091842,
                17117.0,
                17117.0,
                17117.0,
                17117.0,
                17117.0,
                17117.0,
                17117.0,
                17117.0,
                17117.0,
                17117.0,
                17117.0,
                17117.0,
                17117.0,
                17117.0,
                17117.0,
                17117.0,
                17117.0,
                17117.0,
                17117.0,
                17117.0,
                17117.0,
                17117.0,
                17117.0,
                17117.0,
                17117.0,
                17117.0,
                17117.0,
                17117.0,
                17117.0,
                17117.0,
                17117.0,
                17903.94813654971,
                20409.612209401712,
                22846.874589788884,
                21159.094813207405,
                20897.621165020784,
                17896.493775962343,
                17117.0,
                17117.0,
                17117.0,
                17117.0,
                17117.0,
                17117.0,
                17117.0,
                17117.0,
                19152.07986041969,
                18084.77725686386,
                17117.0,
                17117.0,
                17117.0,
                17117.0,
                17117.0,
                17117.0,
                17117.0,
                17117.0,
                17183.88389692115,
                17117.0,
                17117.0,
                17336.926277650346,
                17117.0,
                17117.0,
                17117.0,
                18117.064272664822,
                19244.835225266135,
                17391.28358699838,
                17117.0,
                17117.0,
                17117.0,
                17117.0,
                17117.0,
                17117.0,
                17117.0,
                17117.0,
                17117.0,
                17117.0
            ]
        },
        {
            "flows": [
                1.8920799538493156,
                13.595531582832336,
                3.925470006465912,
                9.01048900523885,
                3.006298596352531,
                2.945190851582229,
                3.8115772801207157,
                3.7070823993591655,
                0.052007348835468294,
                7.617340477132198,
                3.6759604362150844,
                2.4396677635271935,
                2.654739137434032,
                2.563309037685394,
                4.393227881193161,
                4.1201666404640935,
                2.597604866325855,
                3.8712945502907434,
                3.1937719448975663,
                3.2028771036438086,
                3.495353264602761,
                3.3892629416143447,
                2.493380160629749,
                4.896992417066609,
                3.7431961132940423,
                3.208898587524891,
                3.414438062532782,
                2.6274016681798256,
                2.5389681727596085,
                1.8492168424572932,
                1.718658730944153,
                1.716569314888887,
                1.713484171954147,
                1.7124721373592022,
                1.71268264701117,
                1.713844605180485,
                1.7129152494955875,
                1.709792012445622,
                1.7074607817342702,
                1.7069623260764233,
                1.709111460031741,
                1.7091173235778923,
                1.7053577360399748,
                1.6943465031875369,
                1.682265285881246,
                1.6740129746043466,
                1.6767376431557932,
                1.6887065384620816,
                1.7030466689829498,
                1.7126639987454433,
                1.710929237774253,
                1.7033696360540893,
                1.6937510839271028,
                1.6909748338436152,
                1.6930932913239263,
                1.7310576224409144,
                0.1679743707180023,
                0.2463693544268608,
                5.609959100983113,
                1.4643823177371653,
                0.7291634859641393,
                1.5777542725919353,
                2.157936170172559,
                3.44711102129096,
                2.746035304676722,
                2.792625591904709,
                2.2454013776567607,
                1.9504592671792085,
                1.7127097132079587,
                0.9888307988643646,
                2.3830597393778428,
                2.4916835585858808,
                2.1622546053571083,
                2.566480262354946,
                2.548701981181673,
                2.766514883414509,
                2.0768147918914717,
                1.6009147978409277,
                1.7387998469891721,
                1.6602087792949736,
                1.5924111021192868,
                1.5331166744474225,
                1.6399890728738522,
                1.7899742076992455,
                1.810397145477489,
                1.6870443952357326,
                0.69526277333498,
                0.5136475801467896,
                3.8266665587377307,
                1.2599911660007395,
                0.8454279034300028,
                1.579579802539851,
                1.9160986420085424,
                2.0609384202027203,
                1.3270876969669028,
                1.4348161675080822,
                1.8342554227877796,
                1.6793282614050906,
                1.4534371270525783
            ],
            "id": "dam5_dam1copy",
            "objective_function_details": {
                "income_from_energy_eur": 348.62232326850324,
                "limit_zones": 0.0,
                "startups": 9.0,
                "total_income_eur": -101.37767673149676
            },
            "power": [
                1.1194685676127278,
                0.13297264858973115,
                4.581537213862782,
                1.1113904208276009,
                3.154608806402256,
                0.5198865967268603,
                0.4805626313422678,
                1.038098342299905,
                0.970853951439463,
                0.0,
                2.349665568980696,
                0.950826391823596,
                0.29055187439631475,
                0.3524429172472035,
                0.32613209717565306,
                1.4124012753974506,
                1.2366813102986527,
                0.3360014003815411,
                1.0765275115296915,
                0.6405291682442673,
                0.6463885065115251,
                0.8346023323138139,
                0.7663312448351571,
                0.3060086793179135,
                1.7365830832049007,
                0.9940937951290365,
                0.6502634428979623,
                0.7825319013521145,
                0.34457601962009377,
                0.3191275317293838,
                0.1206379402754801,
                0.08306726070335341,
                0.08246598989608261,
                0.08157817897961066,
                0.08128694600264816,
                0.08134752431976118,
                0.08168190077136261,
                0.08141446028650003,
                0.08051568703471142,
                0.07984482927604901,
                0.07970138879897076,
                0.08031984461345067,
                0.08032153196486111,
                0.07923963627049636,
                0.07607093616907538,
                0.07259432687230101,
                0.07021956103722207,
                0.07100363831821391,
                0.0744479247372897,
                0.07857458100228773,
                0.08134215791235781,
                0.08084294612208726,
                0.07866752116664444,
                0.07589959249700803,
                0.07510067160967349,
                0.07571029966156155,
                0.0866352870333567,
                0.0,
                0.0,
                2.0173048302516388,
                0.009894192154579966,
                0.0,
                0.04251921513436991,
                0.20947803458203143,
                0.8035575553677938,
                0.3787151955904237,
                0.3921224724905638,
                0.23464787846237725,
                0.14977245098682263,
                0.08135531315336945,
                0.0,
                0.27426179550441526,
                0.30552044851392257,
                0.2107207497430528,
                0.327044679814373,
                0.32192862767817937,
                0.38460859954374366,
                0.18613375306229404,
                0.04918411448659793,
                0.0888632653206251,
                0.06624713073236652,
                0.046737007804111344,
                0.02967386315033743,
                0.06042851017952584,
                0.10358970005733688,
                0.1094668044539537,
                0.0739696101397792,
                0.0,
                0.0,
                1.0478085725210398,
                0.0,
                0.0,
                0.04304454749348235,
                0.1398845012974223,
                0.18156501300797712,
                0.0,
                0.001385947484340209,
                0.11633249576626756,
                0.07174913997268798
            ],
            "volume": [
                49431.95491463824,
                40233.75855449528,
                39707.88091803506,
                34045.0,
                34045.0,
                34045.0,
                34045.0,
                34045.0,
                37521.70605721915,
                34045.0,
                34045.0,
                34045.0,
                34045.0,
                34288.009673310735,
                34105.69718353287,
                34045.0,
                34710.317292217645,
                34045.0,
                34045.0,
                34045.0,
                34045.0,
                34045.0,
                35162.55379539927,
                34045.0,
                34045.0,
                34189.70503686578,
                34045.0,
                34045.0,
                34045.0,
                34045.0,
                34045.0,
                34045.0,
                34045.0,
                34045.0,
                34045.0,
                34045.0,
                34045.0,
                34045.0,
                34045.0,
                34045.0,
                34045.0,
                34045.0,
                34045.0,
                34045.0,
                34045.0,
                34045.0,
                34045.0,
                34045.0,
                34045.0,
                34045.0,
                34045.0,
                34045.0,
                34045.0,
                34045.0,
                34045.0,
                34045.0,
                35554.915137643744,
                37205.11057376539,
                34045.0,
                34045.0,
                34045.0,
                34045.0,
                34045.0,
                34045.0,
                34045.0,
                34045.0,
                34045.0,
                34045.0,
                34045.0,
                34502.62519269484,
                34045.0,
                34045.0,
                34045.0,
                34045.0,
                34045.0,
                34045.0,
                34045.0,
                34045.0,
                34045.0,
                34045.0,
                34045.0,
                34045.0,
                34045.0,
                34045.0,
                34045.0,
                34045.0,
                34930.18658492209,
                35953.24971998998,
                34045.0,
                34045.0,
                34045.0,
                34045.0,
                34045.0,
                34045.0,
                34045.0,
                34045.0,
                34045.0,
                34045.0,
                34045.0
            ]
        },
        {
            "flows": [
                1.8920799538493156,
                13.595531582832336,
                3.925470006465912,
                11.310214132070541,
                9.749132549762725,
                10.472508670332568,
                2.945190851582229,
                3.8115772801207157,
                0.052007348835468294,
                3.7070823993591655,
                7.617340477132198,
                3.6759604362150844,
                2.4396677635271935,
                2.563309037685394,
                2.654739137434032,
                4.393227881193161,
                2.597604866325855,
                4.1201666404640935,
                3.8712945502907434,
                3.1937719448975663,
                3.2028771036438086,
                3.495353264602761,
                2.493380160629749,
                3.3892629416143447,
                4.896992417066609,
                3.208898587524891,
                3.7431961132940423,
                3.414438062532782,
                2.6274016681798256,
                2.5389681727596085,
                1.8492168424572932,
                1.718658730944153,
                1.716569314888887,
                1.713484171954147,
                1.7124721373592022,
                1.71268264701117,
                1.713844605180485,
                1.7129152494955875,
                1.709792012445622,
                1.7074607817342702,
                1.7069623260764233,
                1.709111460031741,
                1.7091173235778923,
                1.7053577360399748,
                1.6943465031875369,
                1.682265285881246,
                1.6740129746043466,
                1.6767376431557932,
                1.6887065384620816,
                1.7030466689829498,
                1.7126639987454433,
                1.710929237774253,
                1.7033696360540893,
                1.6937510839271028,
                1.6909748338436152,
                1.6930932913239263,
                0.1679743707180023,
                0.2463693544268608,
                1.7310576224409144,
                2.353309024870396,
                4.7210323938498835,
                0.7291634859641393,
                1.5777542725919353,
                2.157936170172559,
                3.44711102129096,
                2.746035304676722,
                2.792625591904709,
                2.2454013776567607,
                1.9504592671792085,
                0.9888307988643646,
                1.7127097132079587,
                2.3830597393778428,
                2.4916835585858808,
                2.1622546053571083,
                2.566480262354946,
                2.548701981181673,
                2.766514883414509,
                2.0768147918914717,
                1.6009147978409277,
                1.7387998469891721,
                1.6602087792949736,
                1.5924111021192868,
                1.5331166744474225,
                1.6399890728738522,
                1.7899742076992455,
                1.810397145477489,
                0.69526277333498,
                0.5136475801467896,
                1.6870443952357326,
                3.80312557220459,
                1.2835321525338805,
                0.8454279034300028,
                1.579579802539851,
                1.9160986420085424,
                1.9026389718055725,
                1.4853871453640508,
                1.4348161675080822,
                1.8342554227877796,
                1.6793282614050906
            ],
            "id": "dam6_dam1copy",
            "objective_function_details": {
                "income_from_energy_eur": 404.37384003428275,
                "limit_zones": 0.0,
                "startups": 9.0,
                "total_income_eur": -45.62615996571725
            },
            "power": [
                1.1194685676127278,
                0.13297264858973115,
                4.581537213862782,
                1.1113904208276009,
                3.9270566293723146,
                3.479986317068198,
                3.687150370376932,
                0.4805626313422678,
                1.038098342299905,
                0.0,
                0.970853951439463,
                2.349665568980696,
                0.950826391823596,
                0.29055187439631475,
                0.32613209717565306,
                0.3524429172472035,
                1.4124012753974506,
                0.3360014003815411,
                1.2366813102986527,
                1.0765275115296915,
                0.6405291682442673,
                0.6463885065115251,
                0.8346023323138139,
                0.3060086793179135,
                0.7663312448351571,
                1.7365830832049007,
                0.6502634428979623,
                0.9940937951290365,
                0.7825319013521145,
                0.34457601962009377,
                0.3191275317293838,
                0.1206379402754801,
                0.08306726070335341,
                0.08246598989608261,
                0.08157817897961066,
                0.08128694600264816,
                0.08134752431976118,
                0.08168190077136261,
                0.08141446028650003,
                0.08051568703471142,
                0.07984482927604901,
                0.07970138879897076,
                0.08031984461345067,
                0.08032153196486111,
                0.07923963627049636,
                0.07607093616907538,
                0.07259432687230101,
                0.07021956103722207,
                0.07100363831821391,
                0.0744479247372897,
                0.07857458100228773,
                0.08134215791235781,
                0.08084294612208726,
                0.07866752116664444,
                0.07589959249700803,
                0.07510067160967349,
                0.07571029966156155,
                0.0,
                0.0,
                0.0866352870333567,
                0.26570043881162475,
                1.6233495497459898,
                0.0,
                0.04251921513436991,
                0.20947803458203143,
                0.8035575553677938,
                0.3787151955904237,
                0.3921224724905638,
                0.23464787846237725,
                0.14977245098682263,
                0.0,
                0.08135531315336945,
                0.27426179550441526,
                0.30552044851392257,
                0.2107207497430528,
                0.327044679814373,
                0.32192862767817937,
                0.38460859954374366,
                0.18613375306229404,
                0.04918411448659793,
                0.0888632653206251,
                0.06624713073236652,
                0.046737007804111344,
                0.02967386315033743,
                0.06042851017952584,
                0.10358970005733688,
                0.1094668044539537,
                0.0,
                0.0,
                0.0739696101397792,
                1.0326595117427686,
                0.0,
                0.0,
                0.04304454749348235,
                0.1398845012974223,
                0.13601121490807846,
                0.01593874686735277,
                0.001385947484340209,
                0.11633249576626756
            ],
            "volume": [
                49905.689017052624,
                39372.582550967905,
                48075.63796969769,
                41429.36825665352,
                40764.58906658203,
                34045.0,
                34045.0,
                34045.0,
                37334.56754547133,
                34045.0,
                34045.0,
                34045.0,
                34045.0,
                34127.287089773774,
                34045.0,
                34045.0,
                35415.305596724414,
                34045.0,
                34045.0,
                34045.0,
                34045.0,
                34045.0,
                34851.294502886136,
                34045.0,
                34045.0,
                34525.867773192236,
                34045.0,
                34045.0,
                34045.0,
                34045.0,
                34045.0,
                34045.0,
                34045.0,
                34045.0,
                34045.0,
                34045.0,
                34045.0,
                34045.0,
                34045.0,
                34045.0,
                34045.0,
                34045.0,
                34045.0,
                34045.0,
                34045.0,
                34045.0,
                34045.0,
                34045.0,
                34045.0,
                34045.0,
                34045.0,
                34045.0,
                34045.0,
                34045.0,
                34045.0,
                34045.0,
                35451.77492655062,
                35381.21944121265,
                34045.0,
                36975.985068501446,
                34045.0,
                34045.0,
                34045.0,
                34045.0,
                34045.0,
                34045.0,
                34045.0,
                34045.0,
                34045.0,
                34696.491022909235,
                34045.0,
                34045.0,
                34045.0,
                34045.0,
                34045.0,
                34045.0,
                34045.0,
                34045.0,
                34045.0,
                34045.0,
                34045.0,
                34045.0,
                34045.0,
                34045.0,
                34045.0,
                34045.0,
                34937.60345971068,
                35101.05713358005,
                34045.0,
                34066.18688787983,
                34045.0,
                34045.0,
                34045.0,
                34045.0,
                34187.46950355743,
                34045.0,
                34045.0,
                34045.0,
                34045.0
            ]
        }
    ],
    "instance_datetimes": {
        "end_decisions": "2020-11-04 23:45",
        "end_impact": "2020-11-05 00:30",
        "end_information": "2020-11-05 00:30",
        "start": "2020-11-04 00:00",
        "start_information": "2020-11-04 00:00"
    },
    "instance_name": "Percentile10",
    "objective_function": 13.070043653749508,
    "price": [
        30.7,
        30.7,
        30.7,
        30.7,
        30.05,
        30.05,
        30.05,
        30.05,
        30.56,
        30.56,
        30.56,
        30.56,
        29.8,
        29.8,
        29.8,
        29.8,
        30.26,
        30.26,
        30.26,
        30.26,
        33.01,
        33.01,
        33.01,
        33.01,
        41.28,
        41.28,
        41.28,
        41.28,
        43.15,
        43.15,
        43.15,
        43.15,
        45.03,
        45.03,
        45.03,
        45.03,
        46.03,
        46.03,
        46.03,
        46.03,
        45.0,
        45.0,
        45.0,
        45.0,
        44.27,
        44.27,
        44.27,
        44.27,
        44.16,
        44.16,
        44.16,
        44.16,
        43.95,
        43.95,
        43.95,
        43.95,
        43.72,
        43.72,
        43.72,
        43.72,
        43.74,
        43.74,
        43.74,
        43.74,
        41.55,
        41.55,
        41.55,
        41.55,
        39.25,
        39.25,
        39.25,
        39.25,
        40.49,
        40.49,
        40.49,
        40.49,
        41.85,
        41.85,
        41.85,
        41.85,
        42.82,
        42.82,
        42.82,
        42.82,
        36.3,
        36.3,
        36.3,
        36.3,
        34.51,
        34.51,
        34.51,
        34.51,
        29.6,
        29.6,
        29.6,
        29.6,
        26.8,
        26.8,
        26.8
    ],
    "solution_datetime": "2024-05-18 23:33",
    "solver": "rl-random",
    "time_step_minutes": 15
}